topspin/__init__.py
topspin/version.py
topspin/dataset/__init__.py
topspin/dataset/helper.py
topspin/dataset/offline_bigdataset.py
topspin/dataset/offline_smalldataset.py
topspin/dataset/offline_varible_smalldataset.py
topspin/dataset/online_dataset.py
topspin/dataset/online_dataset_TEST.py
topspin/estimator/__init__.py
topspin/estimator/model.py
topspin/estimator/param.py
topspin/estimator/predict.py
topspin/estimator/starter.py
topspin/estimator/stopper.py
topspin/estimator/train.py
topspin/mem_dataset/__init__.py
topspin/mem_dataset/bindataset.py
topspin/mem_dataset/bindataset_TEST.py
topspin/mem_dataset/dataset_base.py
topspin/optimizer/__init__.py
topspin/optimizer/lamb_optimizer.py
topspin/regularizers/__init__.py
topspin/regularizers/r_drop.py
topspin/regularizers/smart.py
topspin/regularizers/vat.py
topspin/tools/__init__.py
topspin/tools/draw_figure.py
topspin/tools/figure_drawer.py
topspin/tools/helper.py
topspin/tools/measure.py
topspin/tools/measure_TEST.py
topspin/tools/nn_helper.py
TopSpin-1.2.1.dist-info/METADATA
TopSpin-1.2.1.dist-info/WHEEL
TopSpin-1.2.1.dist-info/top_level.txt
TopSpin-1.2.1.dist-info/RECORD
