Metadata-Version: 2.1
Name: TopSpin
Version: 1.2.1
Summary: A PyTorch based high-level Deep Learning training framework. Seamlessly switch between single-GPU and multi-server; Supports gradient accumulation, learning rate warmup and decay, early stop, mixed precision training, and AutoML.
Home-page: https://github.com/SummerRainET2008/TopSpin
Author-email: tianxia0209@gmail.com
Classifier: Programming Language :: Python :: 3
Classifier: License :: OSI Approved :: MIT License
Classifier: Operating System :: OS Independent
Requires-Python: >=3.8
